snakemake_wrapper_utils/__init__.py
snakemake_wrapper_utils/bcftools.py
snakemake_wrapper_utils/gatk.py
snakemake_wrapper_utils/java.py
snakemake_wrapper_utils/samtools.py
snakemake_wrapper_utils/snakemake.py
snakemake_wrapper_utils-0.8.0.dist-info/LICENSE.md
snakemake_wrapper_utils-0.8.0.dist-info/METADATA
snakemake_wrapper_utils-0.8.0.dist-info/WHEEL
snakemake_wrapper_utils-0.8.0.dist-info/RECORD
