Metadata-Version: 2.3
Name: snakemake-wrapper-utils
Version: 0.8.0
Summary: A collection of utils for Snakemake wrappers.
License: MIT
Author: Johannes Köster
Author-email: johannes.koester@tu-dortmund.de
Requires-Python: >=3.8,<4.0
Classifier: License :: OSI Approved :: MIT License
Classifier: Programming Language :: Python :: 3
Classifier: Programming Language :: Python :: 3.8
Classifier: Programming Language :: Python :: 3.9
Classifier: Programming Language :: Python :: 3.10
Classifier: Programming Language :: Python :: 3.11
Classifier: Programming Language :: Python :: 3.12
Classifier: Programming Language :: Python :: 3.13
